oidfpolicy-0.2.0.dist-info/METADATA
oidfpolicy-0.2.0.dist-info/WHEEL
oidfpolicy-0.2.0.dist-info/licenses/LICENSE
oidfpolicy.pyi
oidfpolicy/__init__.py
oidfpolicy/__init__.pyi
oidfpolicy/oidfpolicy.abi3.so
oidfpolicy/py.typed
py.typed
oidfpolicy-0.2.0.dist-info/RECORD
