Metadata-Version: 2.4
Name: oidfpolicy
Version: 0.2.0
Classifier: Programming Language :: Rust
Classifier: Programming Language :: Python :: Implementation :: CPython
Classifier: Programming Language :: Python :: Implementation :: PyPy
Classifier: Topic :: Software Development :: Libraries
Classifier: Topic :: Software Development :: Libraries :: Python Modules
License-File: LICENSE
Home-Page: https://github.com/SUNET/oidfpolicy
Author-email: Kushal Das <kushal@sunet.se>
Requires-Python: >=3.10
Project-URL: Homepage, https://github.com/SUNET/oidfpolicy
Project-URL: Bug Tracker, https://github.com/SUNET/oidfpolic
